VMCalculator/__init__.py
VMCalculator-0.0.1.dist-info/License.txt
VMCalculator-0.0.1.dist-info/METADATA
VMCalculator-0.0.1.dist-info/WHEEL
VMCalculator-0.0.1.dist-info/top_level.txt
VMCalculator-0.0.1.dist-info/RECORD
